Loden1/AbsCommand.py
Loden1/AbsGrid.py
Loden1/GridCommander.py
Loden1/GridCommands.py
Loden1/GridGrammer.py
Loden1/GridTK.py
Loden1/__init__.py
Loden_9000-1.0.0.dist-info/METADATA
Loden_9000-1.0.0.dist-info/WHEEL
Loden_9000-1.0.0.dist-info/top_level.txt
Loden_9000-1.0.0.dist-info/RECORD
