Metadata-Version: 2.1
Name: Loden-9000
Version: 1.0.0
Summary: Making faces, in time.
Author-email: Randall Nagy <r.a.nagy@gmail.com>
Project-URL: Homepage, https://github.com/Python3-Training/Loden
Project-URL: Bug Tracker, https://github.com/Python3-Training/Loden/issues
Classifier: Programming Language :: Python :: 3
Classifier: License :: OSI Approved :: MIT License
Classifier: Operating System :: OS Independent
Requires-Python: >=3.6
